.coveragerc
.testr.conf
AUTHORS
CONTRIBUTING.rst
ChangeLog
HACKING.rst
LICENSE
MANIFEST.in
README.md
README.rst
babel.cfg
openstack-common.conf
requirements.txt
setup.cfg
setup.py
test-requirements.txt
tox.ini
baremetal_network_provisioning/__init__.py
baremetal_network_provisioning.egg-info/PKG-INFO
baremetal_network_provisioning.egg-info/SOURCES.txt
baremetal_network_provisioning.egg-info/dependency_links.txt
baremetal_network_provisioning.egg-info/entry_points.txt
baremetal_network_provisioning.egg-info/not-zip-safe
baremetal_network_provisioning.egg-info/requires.txt
baremetal_network_provisioning.egg-info/top_level.txt
baremetal_network_provisioning/common/__init__.py
baremetal_network_provisioning/common/constants.py
baremetal_network_provisioning/common/exceptions.py
baremetal_network_provisioning/db/__init__.py
baremetal_network_provisioning/db/bm_nw_provision_db.py
baremetal_network_provisioning/db/bm_nw_provision_models.py
baremetal_network_provisioning/db/migration/__init__.py
baremetal_network_provisioning/db/migration/alembic_migrations/README
baremetal_network_provisioning/db/migration/alembic_migrations/__init__.py
baremetal_network_provisioning/db/migration/alembic_migrations/env.py
baremetal_network_provisioning/db/migration/alembic_migrations/versions/3297cd3f2323_bm_nw_provision_models.py
baremetal_network_provisioning/db/migration/alembic_migrations/versions/HEAD
baremetal_network_provisioning/db/migration/alembic_migrations/versions/__init__.py
baremetal_network_provisioning/db/migration/alembic_migrations/versions/start_bm_nw_provisioning.py
baremetal_network_provisioning/ml2/__init__.py
baremetal_network_provisioning/ml2/hp_network_provisioning_driver.py
baremetal_network_provisioning/ml2/mechanism_hp.py
baremetal_network_provisioning/ml2/network_provisioning_api.py
baremetal_network_provisioning/tests/__init__.py
baremetal_network_provisioning/tests/unit/__init__.py
baremetal_network_provisioning/tests/unit/db/__init__.py
baremetal_network_provisioning/tests/unit/db/test_bm_nw_provision_db.py
baremetal_network_provisioning/tests/unit/ml2/__init__.py
baremetal_network_provisioning/tests/unit/ml2/test_hp_network_provisioning_driver.py
baremetal_network_provisioning/tests/unit/ml2/test_mechanism_hp.py
doc/source/conf.py
doc/source/contributing.rst
doc/source/index.rst
doc/source/installation.rst
